README.md
setup.py
hzon_tools/__init__.py
hzon_tools.egg-info/PKG-INFO
hzon_tools.egg-info/SOURCES.txt
hzon_tools.egg-info/dependency_links.txt
hzon_tools.egg-info/requires.txt
hzon_tools.egg-info/top_level.txt
hzon_tools/db/__init__.py
hzon_tools/db/memorydb.py
hzon_tools/db/mongodb.py
hzon_tools/db/mysqldb.py
hzon_tools/db/redisdb.py
hzon_tools/fd/__init__.py
hzon_tools/fd/perfect_dict.py
hzon_tools/fd/tools.py
hzon_tools/mc/__init__.py
hzon_tools/mc/mc_tools.py
hzon_tools/xc/__init__.py
hzon_tools/xc/config_utils.py
hzon_tools/xc/date_utils.py
hzon_tools/xc/excel_utils.py
hzon_tools/xc/file_utils.py
hzon_tools/xc/html_utils.py
hzon_tools/xc/json_utils.py
hzon_tools/xc/network_utils.py
hzon_tools/xc/os_utils.py
hzon_tools/xc/pdf_utils.py
hzon_tools/xc/photo_utils.py
hzon_tools/xc/string_utils.py
hzon_tools/xc/window_utils.py