Metadata-Version: 2.1
Name: hzon_tools
Version: 0.0.5
Summary: 勇哥python工具包
Author: 勇哥的ID
Author-email: 
Keywords: python,hzon_tools,hzon,spider,windows,mac,linux
Classifier: Development Status :: 1 - Planning
Classifier: Intended Audience :: Developers
Classifier: Programming Language :: Python :: 3
Classifier: Operating System :: Unix
Classifier: Operating System :: MacOS :: MacOS X
Classifier: Operating System :: Microsoft :: Windows
Requires-Dist: DBUtils
Requires-Dist: feapder
Requires-Dist: loguru
Requires-Dist: lxml
Requires-Dist: openpyxl
Requires-Dist: pandas
Requires-Dist: prettytable
Requires-Dist: pymongo
Requires-Dist: PyMySQL
Requires-Dist: pywin32
Requires-Dist: redis
Requires-Dist: Requests
Requires-Dist: six
Requires-Dist: tqdm
Requires-Dist: w3lib
